pybas/__init__.py
pybas/formatter.py
pybas/interpreter.py
pybas/repl.py
pybas_retro-1.0.1.dist-info/licenses/LICENSE
pybas_retro-1.0.1.dist-info/METADATA
pybas_retro-1.0.1.dist-info/WHEEL
pybas_retro-1.0.1.dist-info/entry_points.txt
pybas_retro-1.0.1.dist-info/top_level.txt
pybas_retro-1.0.1.dist-info/RECORD
