Metadata-Version: 2.4
Name: pybas-retro
Version: 1.0.1
Summary: A lightweight BASIC language interpreter written in Python
Author-email: PyBAS Development Team <arfan.caesar@gmail.com>
License-Expression: MIT
Project-URL: Homepage, https://github.com/arfan/pybas
Project-URL: Documentation, https://github.com/arfan/pybas#readme
Project-URL: Repository, https://github.com/arfan/pybas.git
Project-URL: Bug Tracker, https://github.com/arfan/pybas/issues
Keywords: basic,interpreter,programming,education,retro,vintage
Classifier: Development Status :: 5 - Production/Stable
Classifier: Intended Audience :: Developers
Classifier: Intended Audience :: Education
Classifier: Operating System :: OS Independent
Classifier: Programming Language :: Python :: 3
Classifier: Programming Language :: Python :: 3.6
Classifier: Programming Language :: Python :: 3.7
Classifier: Programming Language :: Python :: 3.8
Classifier: Programming Language :: Python :: 3.9
Classifier: Programming Language :: Python :: 3.10
Classifier: Programming Language :: Python :: 3.11
Classifier: Programming Language :: Python :: 3.12
Classifier: Topic :: Software Development :: Interpreters
Classifier: Topic :: Education
Classifier: Topic :: Software Development :: Compilers
Requires-Python: >=3.6
License-File: LICENSE
Provides-Extra: dev
Requires-Dist: build; extra == "dev"
Requires-Dist: twine; extra == "dev"
Requires-Dist: pytest; extra == "dev"
Dynamic: license-file
